LICENSE
MANIFEST.in
README
README.rst
setup.cfg
setup.py
txcoroutine/__init__.py
txcoroutine.egg-info/PKG-INFO
txcoroutine.egg-info/SOURCES.txt
txcoroutine.egg-info/dependency_links.txt
txcoroutine.egg-info/requires.txt
txcoroutine.egg-info/top_level.txt