Metadata-Version: 1.0
Name: txcoroutine
Version: 1.0.9
Summary: Coroutines for Twisted with tail call optimization support
Home-page: http://github.com/eallik/txcoroutine/
Author: Erik Allik
Author-email: eallik@gmail.com
License: BSD
Platform: UNKNOWN
